yta_video_manim/__init__.py
yta_video_manim/animations/__init__.py
yta_video_manim/animations/base_manim_animation.py
yta_video_manim/animations/base_manim_animation_wrapper.py
yta_video_manim/animations/base_three_d_manim_animation.py
yta_video_manim/animations/classes/__init__.py
yta_video_manim/animations/classes/image/__init__.py
yta_video_manim/animations/classes/image/opengl_image_mobject.py
yta_video_manim/animations/classes/loading_bar/__init__.py
yta_video_manim/animations/classes/loading_bar/loading_bar_image.py
yta_video_manim/animations/classes/loading_bar/loading_bar_mobject.py
yta_video_manim/animations/classes/loading_bar/loading_bar_with_images_manim_animation.py
yta_video_manim/animations/classes/loading_bar/mobjects/__init__.py
yta_video_manim/animations/classes/loading_bar/mobjects/loading_bar_mobject.py
yta_video_manim/animations/classes/loading_bar/parameter_classes/__init__.py
yta_video_manim/animations/classes/loading_bar/parameter_classes/loading_bar_image.py
yta_video_manim/animations/classes/test/__init__.py
yta_video_manim/animations/classes/test/test_text_manim_animation.py
yta_video_manim/animations/classes/test/test_timeline_manim_animation.py
yta_video_manim/animations/classes/text/__init__.py
yta_video_manim/animations/classes/text/presets/__init__.py
yta_video_manim/animations/classes/text/presets/magazine/__init__.py
yta_video_manim/animations/classes/text/presets/magazine/utils.py
yta_video_manim/animations/classes/text/presets/magazine_text_is_written_manim_animation.py
yta_video_manim/animations/classes/text/presets/magazine_text_static_manim_animation.py
yta_video_manim/animations/classes/text/presets/rain_of_words_manim_animation.py
yta_video_manim/animations/classes/text/presets/simple_text_manim_animation.py
yta_video_manim/animations/classes/text/presets/text.py
yta_video_manim/animations/classes/text/presets/text_triplets_manim_animation.py
yta_video_manim-0.0.11.dist-info/licenses/LICENSE
yta_video_manim-0.0.11.dist-info/METADATA
yta_video_manim-0.0.11.dist-info/WHEEL
yta_video_manim-0.0.11.dist-info/RECORD
