Metadata-Version: 2.4
Name: yta-video-manim
Version: 0.0.11
Summary: Youtube Autonomous Video Manim Module
License-File: LICENSE
Author: danialcala94
Author-email: danielalcalavalera@gmail.com
Requires-Python: ==3.9
Classifier: Programming Language :: Python :: 3
Classifier: Programming Language :: Python :: 3.9
Requires-Dist: manim (>=0.0.19,<9.0.0)
Requires-Dist: opencv-python (>=4.11.0.86,<9.0.0.0)
Requires-Dist: yta_constants (>=0.0.1,<1.0.0)
Requires-Dist: yta_file (>=0.0.1,<1.0.0)
Requires-Dist: yta_google_drive_downloader (>=0.0.1,<1.0.0)
Requires-Dist: yta_positioning (>=0.0.1,<1.0.0)
Requires-Dist: yta_programming (>=0.0.1,<1.0.0)
Requires-Dist: yta_programming_path (>=0.0.1,<1.0.0)
Requires-Dist: yta_text (>=0.0.1,<1.0.0)
